{"menu": {"130079": {"price": "\u00a550", "is_expand": false, "remark": null, "name": "\u9c8d\u6c41\u767d\u7075\u83c7"}, "130064": {"price": "\u00a522", "is_expand": false, "remark": "\u918b\u6c41", "name": "\u9999\u83dc\u82b1\u751f"}, "130065": {"price": "\u00a525", "is_expand": false, "remark": null, "name": "\u849c\u8338\u9ec4\u74dc"}, "130066": {"price": "\u00a525", "is_expand": false, "remark": null, "name": "\u56db\u5ddd\u6ce1\u83dc"}, "130067": {"price": "\u00a540", "is_expand": false, "remark": null, "name": "\u592b\u59bb\u80ba\u7247"}, "130060": {"price": "\u00a528", "is_expand": false, "remark": null, "name": "\u8471\u6cb9\u62cc\u9762"}, "130061": {"price": "\u00a5108", "is_expand": false, "remark": "\u9171\u6cb9", "name": "\u6cb9\u7206\u6cb3\u867e"}, "130062": {"price": "\u00a528", "is_expand": true, "remark": null, "name": "\u86cb\u7092\u996d"}, "130063": {"price": "\u00a558", "is_expand": false, "remark": "\u9e21\u8089(\u5e26\u9aa8),\u8fa3\u9171", "name": "\u53e3\u6c34\u9e21"}, "130086": {"price": "\u00a588", "is_expand": false, "remark": null, "name": "\u6912\u76d0\u8349\u867e(250\u514b)"}, "130087": {"price": "\u00a572", "is_expand": false, "remark": "\u5e26\u58f3,\u756a\u8304\u9171", "name": "\u5e72\u70e7\u660e\u867e(1\u53ea)"}, "130084": {"price": "\u00a542", "is_expand": true, "remark": null, "name": "\u70e4\u6247\u8d1d(3\u53ea)"}, "130085": {"price": "\u00a542", "is_expand": true, "remark": null, "name": "\u849c\u8338\u84b8\u6247\u8d1d(3\u53ea)"}, "130069": {"price": "\u00a538", "is_expand": false, "remark": null, "name": "\u7cd6\u918b\u5c0f\u6392(150\u514b)"}, "130080": {"price": "\u00a555", "is_expand": false, "remark": "\u8fa3\u9171", "name": "\u4e61\u60c5\u56de\u9505\u8089"}, "130081": {"price": "\u00a558", "is_expand": false, "remark": "\u9e3d\u8089(\u5e26\u9aa8)", "name": "\u8106\u76ae\u4e73\u9e3d"}, "130096": {"price": "\u00a535", "is_expand": false, "remark": "\u571f\u8c46,\u9752\u8c46", "name": "\u5927\u70e4\u53cc\u7d20"}, "130109": {"price": "\u00a543", "is_expand": false, "remark": "(14.00-17.00\u4e0d\u63d0\u4f9b);\u732a\u8089\u7cdc,\u9700\u898120\u5206\u949f\u7b49\u5f85\u65f6\u95f4", "name": "\u5de7\u624b\u751f\u714e(12\u4e2a)"}, "130108": {"price": "\u00a542", "is_expand": false, "remark": "\u867e\u4ec1,\u86cb,\u80e1\u841d\u535c,\u9752\u8c46", "name": "\u626c\u5dde\u7092\u996d"}, "130107": {"price": "\u00a538", "is_expand": false, "remark": "\u8089\u4e1d,\u9e21\u6bdb\u83dc", "name": "\u4e0a\u6d77\u7092\u9762"}, "130106": {"price": "\u00a528", "is_expand": false, "remark": "\u8360\u83dc\u8089\u9985", "name": "\u6cb9\u714e\u9984\u9968(10\u4e2a)"}, "130105": {"price": "\u00a518", "is_expand": false, "remark": "(14.00-17.00\u4e0d\u63d0\u4f9b)", "name": "\u871c\u6c41\u53c9\u70e7\u9165(3\u4e2a)"}, "130104": {"price": "\u00a518", "is_expand": false, "remark": "(14.00-17.00\u4e0d\u63d0\u4f9b)", "name": "\u86cb\u631e(3\u4e2a)"}, "130103": {"price": "\u00a558", "is_expand": false, "remark": "\u867e\u4ec1,\u76ee\u9c7c,\u9c7f\u9c7c,\u6d77\u53c2", "name": "\u6d77\u9c9c\u7092\u996d"}, "130101": {"price": "\u00a56", "is_expand": false, "remark": null, "name": "\u767d\u996d"}, "130083": {"price": "\u00a518", "is_expand": false, "remark": null, "name": "\u8c46\u8c49\u84b8\u5c0f\u9c8d\u9c7c(\u5e26\u58f3)"}, "165613": {"price": "\u00a588", "is_expand": false, "remark": "\u59dc", "name": "\u87f9\u7c89\u8c46\u8150"}, "130110": {"price": "\u00a558", "is_expand": false, "remark": "\u867e\u4ec1,\u76ee\u9c7c,\u9c7f\u9c7c,\u6d77\u53c2", "name": "\u6d77\u9c9c\u7092\u9762"}, "130073": {"price": "\u00a540", "is_expand": false, "remark": null, "name": "\u53c9\u70e7"}, "130071": {"price": "\u00a548", "is_expand": false, "remark": "\u8fa3\u6912,\u82b1\u751f", "name": "\u5bab\u7206\u9e21\u4e01"}, "130070": {"price": "\u00a50", "is_expand": false, "remark": null, "name": "\u4e00\u6b21\u6027\u7b77\u5b50"}, "130077": {"price": "\u00a548", "is_expand": false, "remark": "\u9e21\u8089,\u732a\u8089,\u867e\u4ec1,\u82b1\u751f,\u7af9\u7b0b", "name": "\u516b\u5b9d\u8fa3\u9171"}, "130076": {"price": "\u00a552", "is_expand": false, "remark": "\u83e0\u841d,\u6d0b\u8471,\u9752\u7ea2\u6912,\u9178\u751c\u9171\u6c41", "name": "\u5495\u8001\u8089"}, "130075": {"price": "\u00a550", "is_expand": false, "remark": "\u9e21\u8089(\u5e26\u9aa8)", "name": "\u8fa3\u5b50\u9e21"}, "130074": {"price": "\u00a558", "is_expand": false, "remark": "\u80e1\u841d\u535c,\u8611\u83c7", "name": "\u869d\u6cb9\u725b\u67f3"}, "130095": {"price": "\u00a548", "is_expand": false, "remark": null, "name": "\u897f\u82b9\u767e\u5408"}, "130094": {"price": "\u00a538", "is_expand": false, "remark": "\u732a\u8089\u7cdc,\u5e72\u8fa3\u6912", "name": "\u53d9\u5e9c\u5200\u8c46"}, "130097": {"price": "\u00a533", "is_expand": false, "remark": null, "name": "\u767d\u707c\u82a5\u84dd"}, "130078": {"price": "\u00a558", "is_expand": false, "remark": null, "name": "\u6e05\u7092\u91ce\u5c71\u83cc"}, "130091": {"price": "\u00a5188", "is_expand": false, "remark": "\u9c7c\u5757(\u5e26\u9aa8),\u9178\u751c\u9171\u6c41", "name": "\u677e\u9f20\u6842\u9c7c"}, "130090": {"price": "\u00a595", "is_expand": false, "remark": null, "name": "\u6c34\u6676\u867e\u4ec1(200g)"}, "130093": {"price": "\u00a548", "is_expand": false, "remark": null, "name": "\u849c\u8338\u897f\u5170\u82b1"}, "130092": {"price": "\u00a538", "is_expand": false, "remark": "\u732a\u8089\u788e,\u849c,\u59dc,\u8471", "name": "\u9c7c\u9999\u8304\u5b50"}, "130059": {"price": "\u00a5198", "is_expand": false, "remark": null, "name": "\u9ed1\u6912\u725b\u4ed4\u9aa8"}, "130111": {"price": "\u00a588", "is_expand": false, "remark": "\u87f9\u8089,\u87f9\u9ec4,\u8089\u672b\u9985;\u9700\u898120\u5206\u949f\u7b49\u5f85\u65f6\u95f4", "name": "\u87f9\u7c89\u5c0f\u7b3c(12\u4e2a)"}, "130112": {"price": "\u00a536", "is_expand": false, "remark": null, "name": "\u76d0\u9999\u9e45\u809d"}, "130114": {"price": "\u00a548", "is_expand": false, "remark": "\u867e\u7c73,\u9171\u6cb9,\u6d0b\u8471", "name": "\u94c1\u677f\u8304\u5b50"}, "130115": {"price": "\u00a532", "is_expand": false, "remark": null, "name": "\u6842\u82b1\u7cd6\u85d5"}, "130051": {"price": "\u00a5158", "is_expand": false, "remark": "\u97ed\u8471,\u9ec4\u74dc,\u6d77\u9c9c\u9171,\u8584\u997c", "name": "\u5317\u4eac\u7247\u76ae\u9e2d"}, "130055": {"price": "\u00a568", "is_expand": false, "remark": "\u9e45\u8089(\u5e26\u9aa8),\u674e\u5b50\u9171", "name": "\u6df1\u4e95\u70e7\u9e45"}, "130054": {"price": "\u00a5158", "is_expand": false, "remark": "\u53c9\u70e7,\u70e7\u9e45,\u8089\u76ae,\u9cd7\u9c7c", "name": "\u70e7\u5473\u62fc\u76d8(4\u4eba\u4efd)"}, "130057": {"price": "\u00a580", "is_expand": false, "remark": null, "name": "\u897f\u5170\u82b1\u7092\u725b\u8089"}, "130056": {"price": "\u00a568", "is_expand": false, "remark": "\u5e26\u9aa8", "name": "\u98ce\u6c99\u9e21(\u534a\u53ea)"}, "130099": {"price": "\u00a535", "is_expand": false, "remark": null, "name": "\u9999\u83c7\u83dc\u5fc3"}}, "section": {"0": {"items": ["130064", "130069", "130073", "130112", "130066", "130065", "130067", "130115"], "remark": null, "name": "\u51b7\u83dc"}, "1": {"items": ["130059", "130063", "130081", "130075", "130077", "130056", "130071", "130055", "130054", "130051", "130074", "130057", "130080", "130076"], "remark": null, "name": "\u70ed\u83dc"}, "2": {"items": ["130084", "130085", "165613", "130086", "130061", "130087", "130091", "130083", "130090"], "remark": null, "name": "\u6d77\u9c9c"}, "3": {"items": ["130062", "130097", "130094", "130114", "130093", "130095", "130078", "130079", "130099", "130096", "130092"], "remark": null, "name": "\u852c\u83dc"}, "4": {"items": ["130111", "130104", "130109", "130105", "130110", "130103", "130107", "130101", "130060", "130106", "130108"], "remark": null, "name": "\u70b9\u5fc3"}, "5": {"items": ["130070"], "remark": "Sherpa\u2032s \u5916\u9001\u514d\u8d39\u63d0\u4f9b\u4e00\u6b21\u6027\u5200\u53c9\u548c\u6c64\u5319\u5305\uff0c\u4f46\u5982\u679c\u60a8\u60f3\u8981\u4e00\u6b21\u6027\u7b77\u5b50\uff0c\u8bf7\u9009\u62e9\u8fd9\u4e00\u9879", "name": "\u4e00\u6b21\u6027\u7b77\u5b50"}}, "res_info": {"id": "10909B01", "cuisine": "\u4e2d\u56fd\u4e0a\u6d77\u83dc", "name": "\u82d4\u5723\u56ed / Tai Sheng Yuan", "business_hour": ["11:00", "14:00"], "address": "\u9ec4\u6cb3\u8def 50\u53f7"}}